PyZendureSolarflow/Cli.py
PyZendureSolarflow/PyZendureSolarflow.py
PyZendureSolarflow/ZendureHttpApi.py
PyZendureSolarflow/__init__.py
PyZendureSolarflow/devicetypes/ZendureABPack.py
PyZendureSolarflow/devicetypes/ZendureAce.py
PyZendureSolarflow/devicetypes/ZendureAio.py
PyZendureSolarflow/devicetypes/ZendureDeviceBase.py
PyZendureSolarflow/devicetypes/ZendureHyper.py
PyZendureSolarflow/devicetypes/ZendureSolarflowHub.py
PyZendureSolarflow/devicetypes/__init__.py
pyzenduresolarflow-0.1.2.dist-info/LICENSE
pyzenduresolarflow-0.1.2.dist-info/METADATA
pyzenduresolarflow-0.1.2.dist-info/WHEEL
pyzenduresolarflow-0.1.2.dist-info/entry_points.txt
pyzenduresolarflow-0.1.2.dist-info/top_level.txt
pyzenduresolarflow-0.1.2.dist-info/RECORD
