Metadata-Version: 2.1
Name: pyzenduresolarflow
Version: 0.1.2
Summary: A library to connect and control Zendure Solarflow devices
Home-page: https://github.com/nograx/pyzenduresolarflow
Author: Peter Frommert
Author-email: peter@frommert.io
License: MIT
Classifier: License :: OSI Approved :: MIT License
Classifier: Programming Language :: Python :: 3
Classifier: Programming Language :: Python :: 3.7
Classifier: Programming Language :: Python :: 3.8
Classifier: Programming Language :: Python :: 3.9
Classifier: Programming Language :: Python :: 3.10
Classifier: Programming Language :: Python :: 3.11
Classifier: Programming Language :: Python :: 3.12
Classifier: Programming Language :: Python :: Implementation :: CPython
Classifier: Programming Language :: Python :: Implementation :: PyPy
License-File: LICENSE
Requires-Dist: requests
Requires-Dist: cryptography
